{
    "info": {
       "url_png_icon_64x64": "https://frescopool.com/src/fresco_64.png",
       "url_png_logo": "https://frescopool.com/src/fresco_logo_black.png",
       "location": "Frankfurt, Germany",
       "social": {
           "twitter_handle": "PoolVenus",
           "telegram_handle": "frescopool"
          
       },
       "about": {
           "me": "I'm a software developer from Croatia. I have been ADA HODLer since 2017. In March 2020 I decided to have a more active role in Cardano so I made Fresco pool on ITN with a friend (if Fresco is saturated, check out his pool, ticker:|EDEN|). <br/> Get in touch with me:<a href=\"https://www.linkedin.com/in/filip-strelec\">LinkedIn profile</a> ",
           "server": "1 block producer and 2 relays"
           
       }
   },
   "my-pool-ids": [
    "19cb138eab81d3559e70094df2b6cb1742bf275e920300d5c3972253"
   ]
}